wampify/__init__.py
wampify/__wamp_client.py
wampify/background_task.py
wampify/client.py
wampify/endpoints.py
wampify/entrypoints.py
wampify/exceptions.py
wampify/logger.py
wampify/requests.py
wampify/scheduler.py
wampify/settings.py
wampify/signals.py
wampify/story.py
wampify/wamp.py
wampify/wampify.py
wampify-0.1.0.dist-info/LICENSE
wampify-0.1.0.dist-info/METADATA
wampify-0.1.0.dist-info/WHEEL
wampify-0.1.0.dist-info/top_level.txt
wampify-0.1.0.dist-info/RECORD
