Metadata-Version: 2.1
Name: wampify
Version: 0.1.0
Summary: Web Application Messaging Protocol Framework
Home-page: https://github.com/aturkenov/wampify
Author: Aidar Turkenov
Author-email: a.k.turken0v@gmail.com
License: UNKNOWN
Project-URL: Bug Tracker, https://github.com/aturkenov/wampify/issues
Project-URL: Discussions, https://github.com/aturkenov/wampify/discussions
Platform: UNKNOWN
Classifier: Typing :: Typed
Classifier: Topic :: Internet
Classifier: Topic :: Communications
Classifier: Framework :: AsyncIO
Classifier: Programming Language :: Python :: 3
Classifier: Programming Language :: Python :: 3 :: Only
Classifier: Programming Language :: Python :: 3.6
Classifier: Programming Language :: Python :: 3.7
Classifier: Programming Language :: Python :: 3.8
Classifier: Programming Language :: Python :: 3.9
Classifier: Programming Language :: Python :: 3.10
Classifier: License :: OSI Approved :: MIT License
Classifier: Operating System :: OS Independent
Requires-Python: >=3.6
License-File: LICENSE
Requires-Dist: autobahn
Requires-Dist: pydantic
